jsonfield/__init__.py
jsonfield/encoder.py
jsonfield/fields.py
jsonfield/forms.py
jsonfield/json.py
jsonfield-3.0.0.dist-info/LICENSE
jsonfield-3.0.0.dist-info/METADATA
jsonfield-3.0.0.dist-info/WHEEL
jsonfield-3.0.0.dist-info/top_level.txt
jsonfield-3.0.0.dist-info/RECORD
