Metadata-Version: 2.1
Name: jsonfield
Version: 3.0.0
Summary: A reusable Django field that allows you to store validated JSON in your model.
Home-page: https://github.com/rpkilby/jsonfield/
Author: Brad Jasper
Author-email: contact@bradjasper.com
Maintainer: Ryan P Kilby
Maintainer-email: kilbyr@gmail.com
License: MIT
Platform: UNKNOWN
Classifier: Environment :: Web Environment
Classifier: Framework :: Django
Classifier: Framework :: Django :: 2.2
Classifier: Framework :: Django :: 3.0
Classifier: Intended Audience :: Developers
Classifier: Operating System :: OS Independent
Classifier: Programming Language :: Python
Classifier: Programming Language :: Python :: 3
Classifier: Programming Language :: Python :: 3.6
Classifier: Programming Language :: Python :: 3.7
Classifier: Programming Language :: Python :: 3.8
Classifier: Framework :: Django
Requires-Dist: Django (>=2.2)
